[{"number":55,"name":"00055 - ST SERNIN G. ARNOULT","address":"2 RUE GATIEN ARNOULT","latitude":43.608951960496405,"longitude":1.441003598726198},{"number":195,"name":"00195 - LARROUSSE -RIEUX","address":"FACE 15 RUE PIERRE LAROUSSE","latitude":43.59723540303583,"longitude":1.45907112459247},{"number":229,"name":"00229 - IUT RANGUEIL","address":"129 AV DE RANGUEIL","latitude":43.571433064051334,"longitude":1.46278065695466},{"number":65,"name":"00065 - VERDIER - GRAND ROND","address":"2 ALL FORAIN FRANCOIS VERDIER","latitude":43.597074846780274,"longitude":1.452605307400692},{"number":22,"name":"00022 - CARNOT ROLAND","address":"24 BD LAZARE CARNOT","latitude":43.60221990815785,"longitude":1.45195665819857},{"number":236,"name":"00236 - TOEC / LEMIRE","address":"RUE DE L'ABBE JULES LEMIRE","latitude":43.59729443895585,"longitude":1.403872948950036},{"number":111,"name":"00111 - MINIMES PASSERELLE","address":"38B BD DES MINIMES","latitude":43.615259799224134,"longitude":1.442921175845342},{"number":243,"name":"00243 - ETATS-UNIS / FERRY","address":"96 av des Etats-Unis angle rue Jules Ferry","latitude":43.632641237523,"longitude":1.43180804154469},{"number":174,"name":"00174 - MAUNOURY / MELA","address":"41 AV MAURICE BOURGES MAUNOURY","latitude":43.63692179179762,"longitude":1.452693250180783},{"number":137,"name":"00137 - BRUNHES-FONTAINES","address":"47 BD JEAN BRUNHES","latitude":43.60094924792523,"longitude":1.420275802412521},{"number":144,"name":"00144 - SUISSE - LAUSANE","address":"62 BD DE SUISSE","latitude":43.61606217398145,"longitude":1.421715694303944},{"number":40,"name":"00040 - COLOMBETTE","address":"41 RUE DE LA COLOMBETTE","latitude":43.604660136134775,"longitude":1.453588691746783},{"number":3,"name":"00003 - POMME","address":"62 RUE DE LA POMME","latitude":43.60333593826575,"longitude":1.445569311598848},{"number":139,"name":"00139 - BARRIERE DE LOMBEZ","address":"39 BIS AV DE LOMBEZ","latitude":43.5955673906372,"longitude":1.418420510391943},{"number":93,"name":"00093 - PRINTEMPS","address":"57 RUE DU PRINTEMPS","latitude":43.614465544425535,"longitude":1.44361404386217},{"number":81,"name":"00081 - JARDIN RAYMOND VI","address":"ALL CHARLES DE FITTE","latitude":43.59989498759688,"longitude":1.429556601823956},{"number":248,"name":"00248 - BOUQUETINS/E. ROSTAND","address":"RUE DES BOUQUETINS ANGLE RUE EDMOND ROSTAND","latitude":43.64108958806659,"longitude":1.449039275575635},{"number":53,"name":"00053 - PLACE SAINT JULIEN","address":"PL SAINT JULIEN","latitude":43.60863633636605,"longitude":1.437631489341106},{"number":87,"name":"00087 - LASCROSSES LECLERC","address":"47 BD LASCROSSES","latitude":43.609500004240715,"longitude":1.432335729928681},{"number":121,"name":"00121 - SERRES - A. BERNARD","address":"33 AV HONRE SERRES","latitude":43.612327522628846,"longitude":1.438340345212284},{"number":239,"name":"00239 - LESPINET / HERBETTES","address":"FACE AU 127 AVENUE DE LESPINET","latitude":43.577166917623245,"longitude":1.469393836823441},{"number":1,"name":"00001 - POIDS DE L'HUILE","address":"12 RUE DU POIDS DE L'HUILE","latitude":43.604134687021045,"longitude":1.445420780739279},{"number":7,"name":"00007 - PLACE VICTOR HUGO","address":"6 RUE DU REMPART VILLENEUVE","latitude":43.605852162177925,"longitude":1.446593812218414},{"number":259,"name":"00259 - PLACE RICHE","address":"Place Riche / Lalande - 31000 TOULOUSE","latitude":43.64751,"longitude":1.43298},{"number":234,"name":"00234 - LOIN / RAYNAL","address":"RUE LOIN 100M AVT RAYNAL","latitude":43.628236592839514,"longitude":1.451330504561275},{"number":192,"name":"00192 - RTE DE ST SIMON/PRADO","address":"355 route de saint-Simon","latitude":43.587659413053814,"longitude":1.409162125552512},{"number":48,"name":"00048 - PLACE DU SALIN","address":"18 PL DU SALIN","latitude":43.59474911973265,"longitude":1.444132711268797},{"number":175,"name":"00175 - METRO MAUNOURY","address":"Avenue Maurice BOURGES MAUNOURY","latitude":43.6394555737186,"longitude":1.45256734914219},{"number":166,"name":"00166 - RANGUEIL GUYOU","address":"23 RUE GUYOU","latitude":43.574366149048714,"longitude":1.462031097914686},{"number":135,"name":"00135 - BONNEFOY   LEMAITRE","address":"183 RUE DU FB  BONNEFOY","latitude":43.62295,"longitude":1.45872},{"number":115,"name":"00115 - DEMOISELLES MISTRAL","address":"8 ALL DES DEMOISELLES","latitude":43.590622011025665,"longitude":1.453805825078145},{"number":67,"name":"00067 - MUSEUM","address":"35 ALL JULES GUESDE","latitude":43.59468,"longitude":1.44938},{"number":188,"name":"00188 - MURET/LAFAGE","address":"121 AVENUE DE MURET","latitude":43.584282965328995,"longitude":1.427517107421507},{"number":178,"name":"00178 - BRUNAUD / PLANA","address":"AVENUE YVES BRUNAUD","latitude":43.619281402937425,"longitude":1.468753766918999},{"number":41,"name":"00041 - ST AUBIN CAMICHEL","address":"1 RUE CHARLES CAMICHEL","latitude":43.60265364232074,"longitude":1.454436078796189},{"number":90,"name":"00090 - LASCROSSES- A. BERNARD","address":"3B BD LASCROSSES","latitude":43.61146971436288,"longitude":1.437871385550754},]